jmcm/__init__.py
jmcm/joint_model.py
jmcm/core/__init__.py
jmcm/core/base_func.py
jmcm/core/model_fit.py
jmcm/core/read_data.py
jmcm-0.1.4.dist-info/LICENSE.txt
jmcm-0.1.4.dist-info/METADATA
jmcm-0.1.4.dist-info/WHEEL
jmcm-0.1.4.dist-info/top_level.txt
jmcm-0.1.4.dist-info/RECORD
