Metadata-Version: 2.1
Name: jmcm
Version: 0.1.4
Summary: A statistical package for fit the joint mean-covariance models
Home-page: https://github.com/Xuerui-Yang/jmcm
Author: Xuerui Yang
Author-email: xuerui-yang@outlook.com
License: UNKNOWN
Platform: UNKNOWN
Classifier: Programming Language :: Python :: 3
Classifier: License :: OSI Approved :: MIT License
Classifier: Operating System :: OS Independent
Requires-Python: >=3.7
